twc_square/__init__.py
twc_square/twc_square.py
twc_square-0.2.25.dist-info/LICENSE
twc_square-0.2.25.dist-info/METADATA
twc_square-0.2.25.dist-info/WHEEL
twc_square-0.2.25.dist-info/entry_points.txt
twc_square-0.2.25.dist-info/top_level.txt
twc_square-0.2.25.dist-info/RECORD
