Metadata-Version: 2.1
Name: twc-square
Version: 0.2.25
Summary: The twc_square package contains configuration entries for SQuARE, the SPARQL Query Agent-based Reasoning Engine
Home-page: http://packages.python.org/twc_square
Author: Sabbir Rashid
Author-email: rashidsabbir@gmail.com
License: Apache License 2.0
Keywords: rdf semantic inference reasoning engine
Platform: UNKNOWN
Classifier: Development Status :: 5 - Production/Stable
Classifier: Topic :: Utilities
Classifier: License :: OSI Approved :: Apache Software License
